<?xml version="1.0" encoding="utf-8"?>
<License>
  <CustomerName>Teleopti_RC</CustomerName>
  <ExpirationDate>2016-06-10T04:39:21</ExpirationDate>
  <ExpirationGracePeriod>P15D</ExpirationGracePeriod>
  <MaxActiveAgents>15000</MaxActiveAgents>
  <MaxActiveAgentsGrace>5</MaxActiveAgentsGrace>
  <AgentsOrSeats>0</AgentsOrSeats>
  <MaxSeats>15000</MaxSeats>
  <SeatRatio>1.5</SeatRatio>
  <TeleoptiWFM>
    <Base>true</Base>
    <Lifestyle>true</Lifestyle>
    <ShiftTrader>true</ShiftTrader>
    <VacationPlanner>true</VacationPlanner>
    <OvertimeAvailability>true</OvertimeAvailability>
    <Notify>true</Notify>
    <RealtimeAdherence>true</RealtimeAdherence>
    <AgentScheduleMessenger>true</AgentScheduleMessenger>
    <SMSLink>true</SMSLink>
    <CalendarLink>true</CalendarLink>
    <PerformanceManager>true</PerformanceManager>
    <PayrollIntegration>true</PayrollIntegration>
    <MyTeam>true</MyTeam>
    <Version8>true</Version8>
  </TeleoptiWFM>
  <Agreement>Teleopti.Ccc.Infrastructure.Licensing.Agreements.TeleoptiLic_En_Sw_St.txt</Agreement>
  <Signature xmlns="http://www.w3.org/2000/09/xmldsig#">
    <SignedInfo>
      <CanonicalizationMethod Algorithm="http://www.w3.org/TR/2001/REC-xml-c14n-20010315" />
      <SignatureMethod Algorithm="http://www.w3.org/2000/09/xmldsig#rsa-sha1" />
      <Reference URI="">
        <Transforms>
          <Transform Algorithm="http://www.w3.org/2000/09/xmldsig#enveloped-signature" />
        </Transforms>
        <DigestMethod Algorithm="http://www.w3.org/2000/09/xmldsig#sha1" />
        <DigestValue>SFtvzvR3RRb3fqo+guCXa0rouPQ=</DigestValue>
      </Reference>
    </SignedInfo>
    <SignatureValue>vVm/uAKVXGhCRlpBn9724n3bPPiaoctvwAcfxN05ppaXLcqoO1ZcjGKgmQ6/b/ZJEMZDCg2ErrBtKt9nOo3AOstCXYFBwxmodr4Pnj2k8iJcDZUnGdkAKzuHcDzQJYQVPMAmnw7+M6zvK7SCMjdGdUqgkX9YtJDrezhhpEXF9r0=</SignatureValue>
  </Signature>
</License>